renet/__init__.py
renet/renet.py
renet-0.113.dist-info/LICENSE
renet-0.113.dist-info/WHEEL
renet-0.113.dist-info/METADATA
renet-0.113.dist-info/RECORD
